odoo/addons/repair_timesheet/README.rst
odoo/addons/repair_timesheet/__init__.py
odoo/addons/repair_timesheet/__manifest__.py
odoo/addons/repair_timesheet/i18n/ca.po
odoo/addons/repair_timesheet/i18n/es.po
odoo/addons/repair_timesheet/i18n/it.po
odoo/addons/repair_timesheet/i18n/repair_timesheet.pot
odoo/addons/repair_timesheet/models/__init__.py
odoo/addons/repair_timesheet/models/hr_timesheet.py
odoo/addons/repair_timesheet/models/repair.py
odoo/addons/repair_timesheet/readme/CONTRIBUTORS.md
odoo/addons/repair_timesheet/readme/DESCRIPTION.md
odoo/addons/repair_timesheet/readme/USAGE.md
odoo/addons/repair_timesheet/static/description/icon.png
odoo/addons/repair_timesheet/static/description/icon.svg
odoo/addons/repair_timesheet/static/description/index.html
odoo/addons/repair_timesheet/tests/__init__.py
odoo/addons/repair_timesheet/tests/test_repair_timesheet.py
odoo/addons/repair_timesheet/views/repair_views.xml
odoo_addon_repair_timesheet-18.0.1.0.0.2.dist-info/METADATA
odoo_addon_repair_timesheet-18.0.1.0.0.2.dist-info/WHEEL
odoo_addon_repair_timesheet-18.0.1.0.0.2.dist-info/top_level.txt
odoo_addon_repair_timesheet-18.0.1.0.0.2.dist-info/RECORD
